setup.py
Yapps2.egg-info/PKG-INFO
Yapps2.egg-info/SOURCES.txt
Yapps2.egg-info/dependency_links.txt
Yapps2.egg-info/entry_points.txt
Yapps2.egg-info/top_level.txt
yapps/__init__.py
yapps/cli_tool.py
yapps/grammar.py
yapps/parsetree.py
yapps/runtime.py