Metadata-Version: 1.0
Name: Yapps2
Version: 2.2.0
Summary: Yet Another Python Parser System
Home-page: https://github.com/mk-fg/yapps
Author: Mike Kazantsev
Author-email: mk.fraggod@gmail.com
License: MIT
Platform: UNKNOWN
